{
  "title": "Attack on Titan Season 3 Episode 18",
  "anime": "aot",
  "type": "episode",
  "season": "3",
  "episode_number": "18",
  "arc": "return to shiganshina",
  "key_events": ["Armin's is burnt", "Levi's choice", "Erwin's final rest", "Armin gains the Colossal Titan power"],
  "featured_characters": ["Eren Yeager", "Armin Arlert", "Levi Ackerman", "Hange Zoë", "Mikasa Ackerman", "Floch Forster", "Bertholdt Hoover", "Cart Titan"],
  "content": "Eren finds himself alone on a roof with Armin, burnt near death, and the unconscious Bertholdt.\nThe Cart Titan arrives, and the blond man asserts that Eren's father lied to him.\nHe promises a confused Eren that he will save him before fleeing.\nHange takes Ymir's letter from Reiner's possession but the Cart Titan rescues Reiner before she can kill him.\nMikasa finds Levi about to inject Armin with the serum to save him.\nHowever, when Floch Forster, the only surviving recruit from the suicide charge, arrives with Erwin, also close to death, Levi chooses Erwin instead, causing Eren and Mikasa to defy him and attack him in grief.\nHange calms them down and takes them away.\nAlone now, Levi remembers a conversation with Erwin and ultimately chooses to let the Commander finally rest in peace, injecting Armin instead.\nArmin becomes a Titan and eats Bertholdt, gaining the power of the Colossal Titan.\nLevi and Hange mourn the deceased Erwin while the squad extracts a healed Armin from his Titan form.",
  "metadata": {
    "source_file": "Season_3_episode_18.txt",
    "themes": ["sacrifice", "friendship", "integrity", "leadership"]
  }
}